hardware/ascon_cxof128_core.vhd
-- ============================================================================
-- ASCON CXOF128 CORE - Permutation Engine
-- ============================================================================
-- This module implements the heart of the Ascon algorithm: the permutation.
-- The Ascon permutation transforms a 320-bit state (5 x 64-bit words) through
-- 12 rounds of cryptographic mixing to achieve diffusion and confusion.
--
-- Key Features:
-- - 320-bit internal state (S[0] to S[4], each 64 bits)
-- - 12-round permutation (P12) for maximum security
-- - Supports data absorption (XOR input into S[0])
-- - Outputs S[0] for hash squeezing
-- ============================================================================

library IEEE;
use IEEE.STD_LOGIC_1164.ALL;
use IEEE.NUMERIC_STD.ALL;

entity ascon_cxof128_core is
    Port (
        -- Clock and Reset
        clk, rst   : in  std_logic;
        
        -- Control Signals
        start_perm : in  std_logic;  -- Pulse high to start a 12-round permutation
        absorb_en  : in  std_logic;  -- When high, XOR block_in into S[0]
        init_state : in  std_logic;  -- Reset state to Initial Value (IV)
        
        -- Data Interface
        block_in   : in  std_logic_vector(63 downto 0);  -- Input data to absorb
        block_out  : out std_logic_vector(63 downto 0); -- Output = S[0] for squeezing
        
        -- Status Signals
        core_busy  : out std_logic;  -- High when permutation is running
        perm_done  : out std_logic   -- Pulse high when permutation completes
    );
end ascon_cxof128_core;

architecture Behavioral of ascon_cxof128_core is

    -- ========================================================================
    -- STATE DEFINITION
    -- ========================================================================
    -- Ascon uses a 320-bit state split into 5 words of 64 bits each.
    -- S[0] is the "rate" part - used for absorbing input and squeezing output.
    -- S[1..4] are the "capacity" part - provides security margin.
    
    type state_array is array (0 to 4) of std_logic_vector(63 downto 0);
    signal S, S_next : state_array;  -- Current and next state
    
    -- Round counter: 0 to 11 for 12 rounds
    signal round_ctr : integer range 0 to 15;
    signal round_active : std_logic := '0';  -- High when running permutation
    
    -- ========================================================================
    -- ROUND CONSTANTS
    -- ========================================================================
    -- Each round uses a different constant to break symmetry.
    -- These values are part of the Ascon specification.
    
    type round_const_array is array (0 to 11) of std_logic_vector(7 downto 0);
    constant RC_TABLE : round_const_array := (
        x"f0", x"e1", x"d2", x"c3",   -- Rounds 0-3
        x"b4", x"a5", x"96", x"87",   -- Rounds 4-7
        x"78", x"69", x"5a", x"4b"    -- Rounds 8-11
    );

    -- ========================================================================
    -- ROTATE RIGHT FUNCTION
    -- ========================================================================
    -- Rotates a 64-bit value right by n positions.
    -- This is the key operation in the linear diffusion layer.
    -- Example: ROR64(ABCD, 1) = DABC (last bit moves to front)
    
    function ROR64(val : std_logic_vector; n : integer) return std_logic_vector is
    begin
        -- Take lower n bits and concatenate with upper (64-n) bits
        return val(n-1 downto 0) & val(63 downto n);
    end function;

begin

    -- ========================================================================
    -- MAIN STATE MACHINE PROCESS
    -- ========================================================================
    -- Controls the permutation execution and data absorption.
    
    process(clk)
    begin
        if rising_edge(clk) then
        
            -- RESET / INITIALIZE
            -- When reset or init_state is high, load the Initial Value (IV).
            -- The IV for CXOF128 encodes: rate=8 bytes, rounds=12, variant=4
            if rst = '1' or init_state = '1' then
                S(0) <= x"0000080000cc0004";  -- CXOF128 IV (from Ascon spec)
                S(1) <= (others=>'0');         -- Capacity words start at zero
                S(2) <= (others=>'0');
                S(3) <= (others=>'0');
                S(4) <= (others=>'0');
                round_active <= '0';
                round_ctr <= 0;
                perm_done <= '0';
                
            -- PERMUTATION RUNNING
            -- Execute one round per clock cycle
            elsif round_active = '1' then
                S <= S_next;  -- Apply the round function result
                
                if round_ctr = 11 then 
                    -- Last round complete - permutation finished
                    round_active <= '0';
                    perm_done <= '1';
                    round_ctr <= 0;
                else 
                    -- More rounds to go
                    round_ctr <= round_ctr + 1;
                    perm_done <= '0';
                end if;
                
            -- IDLE STATE
            -- Can absorb data or start a new permutation
            else
                perm_done <= '0';
                
                -- ABSORB: XOR input data into rate word S[0]
                -- This is how we feed data into the hash function
                if absorb_en = '1' then 
                    S(0) <= S(0) xor block_in; 
                end if;
                
                -- START PERMUTATION
                -- Begin the 12-round permutation
                if start_perm = '1' then 
                    round_active <= '1';
                    round_ctr <= 0; 
                end if;
            end if;
        end if;
    end process;
    
    -- ========================================================================
    -- OUTPUT SIGNALS
    -- ========================================================================
    
    -- Busy when running or about to run permutation
    core_busy <= round_active or start_perm;
    
    -- Hash output is always S[0] (the rate word)
    block_out <= S(0);

    -- ========================================================================
    -- ROUND FUNCTION (Combinational Logic)
    -- ========================================================================
    -- Computes S_next from S in a single clock cycle.
    -- The round function has 3 layers:
    --   1. Add round constant
    --   2. Substitution (S-box applied to each bit column)
    --   3. Linear diffusion (rotate and XOR)
    
    process(S, round_ctr)
        variable x0, x1, x2, x3, x4 : std_logic_vector(63 downto 0);  -- Working state
        variable t0, t1, t2, t3, t4 : std_logic_vector(63 downto 0);  -- After S-box
        variable rc                 : std_logic_vector(63 downto 0);  -- Round constant
    begin
        -- Copy current state to working variables
        x0 := S(0); x1 := S(1); x2 := S(2); x3 := S(3); x4 := S(4);
        
        -- ====================================================================
        -- LAYER 1: CONSTANT ADDITION
        -- ====================================================================
        -- Add round constant to x2 to break symmetry between rounds
        rc := (others => '0');
        rc(7 downto 0) := RC_TABLE(round_ctr);
        x2 := x2 xor rc;
        
        -- ====================================================================
        -- LAYER 2: SUBSTITUTION (S-box)
        -- ====================================================================
        -- The Ascon S-box operates on 5-bit columns of the state.
        -- It's implemented as a series of XOR and AND-NOT operations.
        
        -- 2A. Linear Input Mixing
        -- These XORs prepare the state for the non-linear layer
        x0 := x0 xor x4;
        x4 := x4 xor x3;
        x2 := x2 xor x1;
        
        -- 2B. Chi Layer (Non-Linear Core)
        -- This is the heart of the S-box. The AND-NOT operation
        -- provides non-linearity essential for cryptographic security.
        -- Formula: t[i] = x[i] XOR (NOT x[i+1] AND x[i+2])
        t0 := x0 xor (not x1 and x2);
        t1 := x1 xor (not x2 and x3);
        t2 := x2 xor (not x3 and x4);
        t3 := x3 xor (not x4 and x0);
        t4 := x4 xor (not x0 and x1);
        
        -- 2C. Linear Output Mixing
        -- Final XORs and bit inversion to complete the S-box
        t1 := t1 xor t0;  -- Mix t1 with t0
        t0 := t0 xor t4;  -- Mix t0 with t4
        t3 := t3 xor t2;  -- Mix t3 with t2
        t2 := not t2;     -- Invert all bits of t2
        
        -- ====================================================================
        -- LAYER 3: LINEAR DIFFUSION
        -- ====================================================================
        -- Each word is XORed with two rotated versions of itself.
        -- This spreads each input bit's influence across many output bits.
        -- The rotation amounts are carefully chosen for optimal diffusion.
        
        S_next(0) <= t0 xor ROR64(t0, 19) xor ROR64(t0, 28);  -- Rotate by 19 and 28
        S_next(1) <= t1 xor ROR64(t1, 61) xor ROR64(t1, 39);  -- Rotate by 61 and 39
        S_next(2) <= t2 xor ROR64(t2, 1)  xor ROR64(t2, 6);   -- Rotate by 1 and 6
        S_next(3) <= t3 xor ROR64(t3, 10) xor ROR64(t3, 17);  -- Rotate by 10 and 17
        S_next(4) <= t4 xor ROR64(t4, 7)  xor ROR64(t4, 41);  -- Rotate by 7 and 41
        
    end process;
    
end Behavioral;

hardware/tb_core_wave.vhd
-- ============================================================================
-- TESTBENCH: ASCON CXOF128 CORE - Waveform Simulation
-- ============================================================================
-- This testbench demonstrates the core permutation module behavior.
-- It shows: initialization, data absorption, and a full P12 permutation.
-- Run with: ghdl -r --std=08 tb_core_wave --vcd=core_wave.vcd --stop-time=500ns
-- ============================================================================

library IEEE;
use IEEE.STD_LOGIC_1164.ALL;
use IEEE.NUMERIC_STD.ALL;

entity tb_core_wave is
end tb_core_wave;

architecture sim of tb_core_wave is

    -- Clock period: 10ns = 100 MHz
    constant CLK_PERIOD : time := 10 ns;
    
    -- Signals to connect to DUT (Device Under Test)
    signal clk        : std_logic := '0';
    signal rst        : std_logic := '1';
    signal start_perm : std_logic := '0';
    signal absorb_en  : std_logic := '0';
    signal init_state : std_logic := '0';
    signal block_in   : std_logic_vector(63 downto 0) := (others => '0');
    signal block_out  : std_logic_vector(63 downto 0);
    signal core_busy  : std_logic;
    signal perm_done  : std_logic;
    
begin

    -- =========================================================================
    -- CLOCK GENERATION
    -- =========================================================================
    clk <= not clk after CLK_PERIOD / 2;
    
    -- =========================================================================
    -- DEVICE UNDER TEST
    -- =========================================================================
    DUT: entity work.ascon_cxof128_core
        port map (
            clk        => clk,
            rst        => rst,
            start_perm => start_perm,
            absorb_en  => absorb_en,
            init_state => init_state,
            block_in   => block_in,
            block_out  => block_out,
            core_busy  => core_busy,
            perm_done  => perm_done
        );
    
    -- =========================================================================
    -- STIMULUS PROCESS
    -- =========================================================================
    stimulus: process
    begin
        -- =====================================================================
        -- PHASE 1: RESET
        -- =====================================================================
        report "=== PHASE 1: RESET ===" severity note;
        rst <= '1';
        wait for CLK_PERIOD * 3;
        rst <= '0';
        wait for CLK_PERIOD * 2;
        
        report "After reset, S[0] (block_out) should be IV: 0x0000080000cc0004";
        report "block_out = 0x" & to_hstring(block_out);
        
        -- =====================================================================
        -- PHASE 2: FIRST P12 PERMUTATION (Initialization)
        -- =====================================================================
        report "=== PHASE 2: FIRST P12 (IV Permutation) ===" severity note;
        
        -- Start P12
        start_perm <= '1';
        wait for CLK_PERIOD;
        start_perm <= '0';
        
        -- Wait for permutation to complete (12 rounds)
        report "core_busy should be '1' during permutation";
        wait until perm_done = '1';
        wait for 0 ns;  -- Delta cycle
        
        report "P12 complete! perm_done = '1'";
        report "New S[0] = 0x" & to_hstring(block_out);
        
        wait for CLK_PERIOD * 2;
        
        -- =====================================================================
        -- PHASE 3: ABSORB DATA
        -- =====================================================================
        report "=== PHASE 3: ABSORB DATA ===" severity note;
        
        -- Absorb a test value into S[0]
        block_in <= x"0000000000000040";  -- z_bit_len = 64 bits = 8 bytes
        absorb_en <= '1';
        wait for CLK_PERIOD;
        absorb_en <= '0';
        block_in <= (others => '0');
        
        report "Absorbed 0x0000000000000040 (XORed into S[0])";
        wait for CLK_PERIOD;
        report "New S[0] = 0x" & to_hstring(block_out);
        
        -- =====================================================================
        -- PHASE 4: SECOND P12 PERMUTATION
        -- =====================================================================
        report "=== PHASE 4: SECOND P12 (After Absorption) ===" severity note;
        
        start_perm <= '1';
        wait for CLK_PERIOD;
        start_perm <= '0';
        
        wait until perm_done = '1';
        wait for 0 ns;
        
        report "Second P12 complete!";
        report "Final S[0] = 0x" & to_hstring(block_out);
        
        wait for CLK_PERIOD * 3;
        
        -- =====================================================================
        -- PHASE 5: REINITIALIZE STATE
        -- =====================================================================
        report "=== PHASE 5: REINITIALIZE ===" severity note;
        
        init_state <= '1';
        wait for CLK_PERIOD;
        init_state <= '0';
        
        report "State reinitialized to IV";
        wait for CLK_PERIOD;
        report "S[0] = 0x" & to_hstring(block_out);
        
        wait for CLK_PERIOD * 5;
        
        report "=== SIMULATION COMPLETE ===" severity note;
        wait;
    end process;

end sim;

hardware/core_wave.vcd
$date
  Tue Dec  9 14:14:34 2025
$end
$version
  GHDL v0
$end
$timescale
  1 fs
$end
$scope module standard $end
$upscope $end
$scope module textio $end
$upscope $end
$scope module std_logic_1164 $end
$upscope $end
$scope module numeric_std $end
$upscope $end
$scope module tb_core_wave $end
$var reg 1 ! clk $end
$var reg 1 " rst $end
$var reg 1 # start_perm $end
$var reg 1 $ absorb_en $end
$var reg 1 % init_state $end
$var reg 64 & block_in[63:0] $end
$var reg 64 ' block_out[63:0] $end
$var reg 1 ( core_busy $end
$var reg 1 ) perm_done $end
$scope module dut $end
$var reg 1 * clk $end
$var reg 1 + rst $end
$var reg 1 , start_perm $end
$var reg 1 - absorb_en $end
$var reg 1 . init_state $end
$var reg 64 / block_in[63:0] $end
$var reg 64 0 block_out[63:0] $end
$var reg 1 1 core_busy $end
$var reg 1 2 perm_done $end
$comment s is not handled $end
$comment s_next is not handled $end
$var integer 32 3 round_ctr $end
$var reg 1 4 round_active $end
$upscope $end
$upscope $end
$enddefinitions $end
#0
0!
1"
0#
0$
0%
b0000000000000000000000000000000000000000000000000000000000000000 &
bUUUUUUUUUUUUUUUUUUUUUUUUUUUUUUUUUUUUUUUUUUUUUUUUUUUUUUUUUUUUUUUU '
0(
U)
0*
1+
0,
0-
0.
b0000000000000000000000000000000000000000000000000000000000000000 /
bUUUUUUUUUUUUUUUUUUUUUUUUUUUUUUUUUUUUUUUUUUUUUUUUUUUUUUUUUUUUUUUU 0
01
U2
b0 3
04
#5000000
1!
b0000000000000000000010000000000000000000110011000000000000000100 '
0)
1*
b0000000000000000000010000000000000000000110011000000000000000100 0
02
#10000000
0!
0*
#15000000
1!
1*
#20000000
0!
0*
#25000000
1!
1*
#30000000
0!
0"
0*
0+
#35000000
1!
1*
#40000000
0!
0*
#45000000
1!
1*
#50000000
0!
1#
1(
0*
1,
11
#55000000
1!
1*
14
#60000000
0!
0#
0*
0,
#65000000
1!
b1000110011011110100001110100000000000001110011001000000011101101 '
1*
b1000110011011110100001110100000000000001110011001000000011101101 0
b1 3
#70000000
0!
0*
#75000000
1!
b0100000011110010111011111001111001100001110110111111100001111111 '
1*
b0100000011110010111011111001111001100001110110111111100001111111 0
b10 3
#80000000
0!
0*
#85000000
1!
b0101101111010101100011010001101010101011110000101010011000000001 '
1*
b0101101111010101100011010001101010101011110000101010011000000001 0
b11 3
#90000000
0!
0*
#95000000
1!
b0111011111000111011000011101011110111100011011111000100111100100 '
1*
b0111011111000111011000011101011110111100011011111000100111100100 0
b100 3
#100000000
0!
0*
#105000000
1!
b1100110101110000001011011011111000010000101010110010101110101101 '
1*
b1100110101110000001011011011111000010000101010110010101110101101 0
b101 3
#110000000
0!
0*
#115000000
1!
b1010010111001100110110111001101001111100110000111011001001110111 '
1*
b1010010111001100110110111001101001111100110000111011001001110111 0
b110 3
#120000000
0!
0*
#125000000
1!
b0000100010010110111111001001101111100100000010001100000110001111 '
1*
b0000100010010110111111001001101111100100000010001100000110001111 0
b111 3
#130000000
0!
0*
#135000000
1!
b0011000010011011000010000010010001101010001100100000001010010010 '
1*
b0011000010011011000010000010010001101010001100100000001010010010 0
b1000 3
#140000000
0!
0*
#145000000
1!
b0110100110000110111111111110101100000000001110100000110001000001 '
1*
b0110100110000110111111111110101100000000001110100000110001000001 0
b1001 3
#150000000
0!
0*
#155000000
1!
b1101101111101001100000110001100011101110011010101101110000011010 '
1*
b1101101111101001100000110001100011101110011010101101110000011010 0
b1010 3
#160000000
0!
0*
#165000000
1!
b1100100010101000010001100010010101011000001101011011011101110110 '
1*
b1100100010101000010001100010010101011000001101011011011101110110 0
b1011 3
#170000000
0!
0*
#175000000
1!
b0110011101010101001001111100001010100000111010001101111000000011 '
0(
1)
1*
b0110011101010101001001111100001010100000111010001101111000000011 0
01
12
b0 3
04
#180000000
0!
0*
#185000000
1!
0)
1*
02
#190000000
0!
0*
#195000000
1!
1$
b0000000000000000000000000000000000000000000000000000000001000000 &
1*
1-
b0000000000000000000000000000000000000000000000000000000001000000 /
#200000000
0!
0*
#205000000
1!
0$
b0000000000000000000000000000000000000000000000000000000000000000 &
b0110011101010101001001111100001010100000111010001101111001000011 '
1*
0-
b0000000000000000000000000000000000000000000000000000000000000000 /
b0110011101010101001001111100001010100000111010001101111001000011 0
#210000000
0!
0*
#215000000
1!
1#
1(
1*
1,
11
#220000000
0!
0*
#225000000
1!
0#
1*
0,
14
#230000000
0!
0*
#235000000
1!
b1011011010111000100101110111100010011000101110100111101010011001 '
1*
b1011011010111000100101110111100010011000101110100111101010011001 0
b1 3
#240000000
0!
0*
#245000000
1!
b0010010011110101001111010101010100100101110101010111001010100000 '
1*
b0010010011110101001111010101010100100101110101010111001010100000 0
b10 3
#250000000
0!
0*
#255000000
1!
b1111110100011001111001101101011100101101011111010101010101110001 '
1*
b1111110100011001111001101101011100101101011111010101010101110001 0
b11 3
#260000000
0!
0*
#265000000
1!
b0110001011010001111010101110111110010111011110010100101010110111 '
1*
b0110001011010001111010101110111110010111011110010100101010110111 0
b100 3
#270000000
0!
0*
#275000000
1!
b0000100000000011110000010010011010000011101111000111001101100001 '
1*
b0000100000000011110000010010011010000011101111000111001101100001 0
b101 3
#280000000
0!
0*
#285000000
1!
b0000110001111010100110111100000100111001101000011101000110001101 '
1*
b0000110001111010100110111100000100111001101000011101000110001101 0
b110 3
#290000000
0!
0*
#295000000
1!
b0001011101000101000010111011001111010100110100010010000000101110 '
1*
b0001011101000101000010111011001111010100110100010010000000101110 0
b111 3
#300000000
0!
0*
#305000000
1!
b0110100111011100010101111101010010001111000011000100000111111101 '
1*
b0110100111011100010101111101010010001111000011000100000111111101 0
b1000 3
#310000000
0!
0*
#315000000
1!
b0010100011011111101111011001010110111100011001110011011101101100 '
1*
b0010100011011111101111011001010110111100011001110011011101101100 0
b1001 3
#320000000
0!
0*
#325000000
1!
b1001010011010101101011010110111010000101010011001110111101010000 '
1*
b1001010011010101101011010110111010000101010011001110111101010000 0
b1010 3
#330000000
0!
0*
#335000000
1!
b1111000001000010110110110100001010011000010011011110101110101011 '
1*
b1111000001000010110110110100001010011000010011011110101110101011 0
b1011 3
#340000000
0!
0*
#345000000
1!
b1011011001011110100011001001110101100111101111000110011110000000 '
0(
1)
1*
b1011011001011110100011001001110101100111101111000110011110000000 0
01
12
b0 3
04
#350000000
0!
0*
#355000000
1!
0)
1*
02
#360000000
0!
0*
#365000000
1!
1*
#370000000
0!
0*
#375000000
1!
1%
1*
1.
#380000000
0!
0*
#385000000
1!
0%
b0000000000000000000010000000000000000000110011000000000000000100 '
1*
0.
b0000000000000000000010000000000000000000110011000000000000000100 0
